CHANGES.txt
MANIFEST.in
README.rst
setup.py
collective/__init__.py
collective.rtvideo.mediacore.egg-info/PKG-INFO
collective.rtvideo.mediacore.egg-info/SOURCES.txt
collective.rtvideo.mediacore.egg-info/dependency_links.txt
collective.rtvideo.mediacore.egg-info/entry_points.txt
collective.rtvideo.mediacore.egg-info/namespace_packages.txt
collective.rtvideo.mediacore.egg-info/not-zip-safe
collective.rtvideo.mediacore.egg-info/requires.txt
collective.rtvideo.mediacore.egg-info/top_level.txt
collective/rtvideo/__init__.py
collective/rtvideo/mediacore/__init__.py
collective/rtvideo/mediacore/config.py
collective/rtvideo/mediacore/configure.zcml
collective/rtvideo/mediacore/interfaces.py
collective/rtvideo/mediacore/jwplayer_template.pt
collective/rtvideo/mediacore/videoembedcode.py
collective/rtvideo/mediacore/jwplayer/jwplayer.js
collective/rtvideo/mediacore/jwplayer/player.swf
collective/rtvideo/mediacore/profiles/default/jsregistry.xml
collective/rtvideo/mediacore/profiles/default/metadata.xml
collective/rtvideo/mediacore/tests/__init__.py
collective/rtvideo/mediacore/tests/base.py
collective/rtvideo/mediacore/tests/test_videoembedcode.py
docs/HISTORY.txt
docs/INTALL.txt
docs/LICENSE.GPL
docs/LICENSE.txt