Metadata-Version: 1.1
Name: collective.rtvideo.mediacore
Version: 2.0.1
Summary: RedTurtle Video integration for MediaCore
Home-page: UNKNOWN
Author: RedTurtle Technology
Author-email: sviluppoplone@redturtle.net
License: GPL
Platform: UNKNOWN
Classifier: Programming Language :: Python
